LICENSE
MANIFEST.in
README.md
setup.py
ifb_openlink.egg-info/PKG-INFO
ifb_openlink.egg-info/SOURCES.txt
ifb_openlink.egg-info/dependency_links.txt
ifb_openlink.egg-info/entry_points.txt
ifb_openlink.egg-info/requires.txt
ifb_openlink.egg-info/top_level.txt
openlink/__init__.py
openlink/asgi.py
openlink/settings.py
openlink/urls.py
openlink/wsgi.py
openlink/core/__init__.py
openlink/core/admin.py
openlink/core/apps.py
openlink/core/connector.py
openlink/core/filters.py
openlink/core/forms.py
openlink/core/models.py
openlink/core/serializers.py
openlink/core/signal.py
openlink/core/tests.py
openlink/core/urls.py
openlink/core/lib/__init__.py
openlink/core/lib/utils.py
openlink/core/migrations/0001_initial.py
openlink/core/migrations/__init__.py
openlink/core/static/ckeditor/ckeditor-init.js
openlink/core/static/ckeditor/ckeditor/CHANGES.md
openlink/core/static/ckeditor/ckeditor/LICENSE.md
openlink/core/static/ckeditor/ckeditor/README.md
openlink/core/static/ckeditor/ckeditor/build-config.js
openlink/core/static/ckeditor/ckeditor/ckeditor.js
openlink/core/static/ckeditor/ckeditor/config.js
openlink/core/static/ckeditor/ckeditor/contents.css
openlink/core/static/ckeditor/ckeditor/styles.js
openlink/core/static/ckeditor/ckeditor/adapters/jquery.js
openlink/core/static/ckeditor/ckeditor/lang/af.js
openlink/core/static/ckeditor/ckeditor/lang/ar.js
openlink/core/static/ckeditor/ckeditor/lang/az.js
openlink/core/static/ckeditor/ckeditor/lang/bg.js
openlink/core/static/ckeditor/ckeditor/lang/bn.js
openlink/core/static/ckeditor/ckeditor/lang/bs.js
openlink/core/static/ckeditor/ckeditor/lang/ca.js
openlink/core/static/ckeditor/ckeditor/lang/cs.js
openlink/core/static/ckeditor/ckeditor/lang/cy.js
openlink/core/static/ckeditor/ckeditor/lang/da.js
openlink/core/static/ckeditor/ckeditor/lang/de-ch.js
openlink/core/static/ckeditor/ckeditor/lang/de.js
openlink/core/static/ckeditor/ckeditor/lang/el.js
openlink/core/static/ckeditor/ckeditor/lang/en-au.js
openlink/core/static/ckeditor/ckeditor/lang/en-ca.js
openlink/core/static/ckeditor/ckeditor/lang/en-gb.js
openlink/core/static/ckeditor/ckeditor/lang/en.js
openlink/core/static/ckeditor/ckeditor/lang/eo.js
