Metadata-Version: 2.1
Name: ifb-openlink
Version: 1.0.0
Summary: A dashboard that establish links between the structure of a research project and multiple data sources 
Home-page: https://gitlab.com/igbmc/openlink
Author: Laurent Bouri, Julien Seiler
License: GNU General Public License v3 (GPLv3)
Project-URL: Bug Tracker, https://gitlab.com/igbmc/openlink/-/issues
Project-URL: Source Code, https://gitlab.com/igbmc/openlink
Keywords: FAIR,open-data,data-managment-tools
Platform: UNKNOWN
Classifier: Programming Language :: Python :: 3
Classifier: Framework :: Django :: 3.0
Classifier: License :: OSI Approved :: GNU General Public License v3 (GPLv3)
Classifier: Topic :: Scientific/Engineering
Classifier: Topic :: System :: Systems Administration
Classifier: Topic :: Internet :: WWW/HTTP :: WSGI :: Application
Requires-Python: >=3.6
License-File: LICENSE
